dragonfly_doe2/__init__.py
dragonfly_doe2/__main__.py
dragonfly_doe2/_extend_dragonfly.py
dragonfly_doe2/writer.py
dragonfly_doe2/cli/__init__.py
dragonfly_doe2/cli/translate.py
dragonfly_doe2/properties/__init__.py
dragonfly_doe2/properties/model.py
dragonfly_doe2/properties/room2d.py
dragonfly_doe2-0.12.14.dist-info/licenses/LICENSE
dragonfly_doe2-0.12.14.dist-info/METADATA
dragonfly_doe2-0.12.14.dist-info/WHEEL
dragonfly_doe2-0.12.14.dist-info/entry_points.txt
dragonfly_doe2-0.12.14.dist-info/top_level.txt
dragonfly_doe2-0.12.14.dist-info/RECORD
